CHEWBBACA/__init__.py
CHEWBBACA/chewBBACA.py
CHEWBBACA/AlleleCall/__init__.py
CHEWBBACA/AlleleCall/allele_call.py
CHEWBBACA/AlleleCallEvaluator/__init__.py
CHEWBBACA/AlleleCallEvaluator/evaluate_calls.py
CHEWBBACA/CHEWBBACA_NS/__init__.py
CHEWBBACA/CHEWBBACA_NS/download_schema.py
CHEWBBACA/CHEWBBACA_NS/stats_requests.py
CHEWBBACA/CHEWBBACA_NS/synchronize_schema.py
CHEWBBACA/CHEWBBACA_NS/upload_schema.py
CHEWBBACA/ComputeMSA/compute_msa.py
CHEWBBACA/CreateSchema/__init__.py
CHEWBBACA/CreateSchema/create_schema.py
CHEWBBACA/ExtractCgMLST/__init__.py
CHEWBBACA/ExtractCgMLST/determine_cgmlst.py
CHEWBBACA/GetAlleles/get_alleles.py
CHEWBBACA/PrepExternalSchema/__init__.py
CHEWBBACA/PrepExternalSchema/adapt_schema.py
CHEWBBACA/SchemaEvaluator/__init__.py
CHEWBBACA/SchemaEvaluator/evaluate_schema.py
CHEWBBACA/UniprotFinder/__init__.py
CHEWBBACA/UniprotFinder/annotate_schema.py
CHEWBBACA/prodigal_training_files/Acinetobacter_baumannii.trn
CHEWBBACA/prodigal_training_files/Campylobacter_jejuni.trn
CHEWBBACA/prodigal_training_files/Enterococcus_faecium.trn
CHEWBBACA/prodigal_training_files/Escherichia_coli.trn
CHEWBBACA/prodigal_training_files/Haemophilus_influenzae.trn
CHEWBBACA/prodigal_training_files/Klebsiella_pneumoniae.trn
CHEWBBACA/prodigal_training_files/Legionella_pneumophila.trn
CHEWBBACA/prodigal_training_files/Listeria_monocytogenes.trn
CHEWBBACA/prodigal_training_files/Pseudomonas_aeruginosa.trn
CHEWBBACA/prodigal_training_files/README.md
CHEWBBACA/prodigal_training_files/Salmonella_enterica.trn
CHEWBBACA/prodigal_training_files/Staphylococcus_aureus.trn
CHEWBBACA/prodigal_training_files/Staphylococcus_haemolyticus.trn
CHEWBBACA/prodigal_training_files/Streptococcus_agalactiae.trn
CHEWBBACA/prodigal_training_files/Streptococcus_canis.trn
CHEWBBACA/prodigal_training_files/Streptococcus_dysgalactiae.trn
CHEWBBACA/prodigal_training_files/Streptococcus_equi.trn
CHEWBBACA/prodigal_training_files/Streptococcus_pneumoniae.trn
chewbbaca-3.5.1.dist-info/licenses/LICENSE
chewbbaca-3.5.1.dist-info/METADATA
chewbbaca-3.5.1.dist-info/WHEEL
chewbbaca-3.5.1.dist-info/entry_points.txt
chewbbaca-3.5.1.dist-info/top_level.txt
chewbbaca-3.5.1.dist-info/RECORD
