Metadata-Version: 2.4
Name: chewBBACA
Version: 3.5.1
Summary: A complete suite for gene-by-gene schema creation and strain identification.
Author: Rafael Mamede, Pedro Cerqueira, Mickael Silva, João Carriço, Mário Ramirez
Maintainer-email: UMMI <imm-bioinfo@medicina.ulisboa.pt>
License:                     GNU GENERAL PUBLIC LICENSE
Project-URL: Repository, https://github.com/B-UMMI/chewBBACA
Project-URL: Documentation, https://chewbbaca.readthedocs.io/en/latest/index.html
Project-URL: Changelog, https://github.com/B-UMMI/chewBBACA/blob/master/CHANGELOG.md
Keywords: bioinformatics,genomics,mlst,bacteria,cgmlst,wgmlst,outbreak detection,allele calling,bacterial typing,bacterial genome analysis
Classifier: Development Status :: 5 - Production/Stable
Classifier: Environment :: Console
Classifier: Intended Audience :: Science/Research
Classifier: License :: OSI Approved :: GNU General Public License v3 (GPLv3)
Classifier: Natural Language :: English
Classifier: Operating System :: Unix
Classifier: Programming Language :: Python :: 3.11
Classifier: Programming Language :: Python :: 3.10
Classifier: Programming Language :: Python :: 3.9
Classifier: Programming Language :: Python :: 3.8
Classifier: Programming Language :: Python :: Implementation :: CPython
Classifier: Topic :: Scientific/Engineering :: Bio-Informatics
Requires-Python: >=3.8
License-File: LICENSE
Requires-Dist: numpy~=1.24.3
Requires-Dist: scipy~=1.10.1
Requires-Dist: biopython>=1.79
Requires-Dist: plotly>=5.8.0
Requires-Dist: SPARQLWrapper>=2.0.0
Requires-Dist: pandas<2.1,>=1.5.1
Requires-Dist: requests>=2.27.1
Requires-Dist: pyrodigal>=3.0.0
Dynamic: license-file
